threadkiller/__init__.py
threadkiller/__main__.py
threadkiller/config.py
threadkiller/handlers.py
threadkiller/strings.py
threadkiller-2.2.3.dist-info/METADATA
threadkiller-2.2.3.dist-info/WHEEL
threadkiller-2.2.3.dist-info/entry_points.txt
threadkiller-2.2.3.dist-info/licenses/LICENSE.txt
threadkiller-2.2.3.dist-info/RECORD
