Metadata-Version: 2.4
Name: threadkiller
Version: 2.2.3
Summary: Telegram bot to delete messages sent outside of threads
License-Expression: EUPL-1.2
License-File: LICENSE.txt
Keywords: telegram,chat-threads,telegram-bot,chat-moderation,python-telegram-bot
Author: Stefano Pigozzi
Author-email: me@steffo.eu
Maintainer: Stefano Pigozzi
Maintainer-email: me@steffo.eu
Requires-Python: >=3.10,<4.0
Classifier: Programming Language :: Python :: 3
Classifier: Programming Language :: Python :: 3.10
Classifier: License :: OSI Approved :: European Union Public Licence 1.2 (EUPL 1.2)
Classifier: Natural Language :: English
Classifier: Operating System :: OS Independent
Classifier: Topic :: Communications :: Chat
Classifier: Typing :: Typed
Requires-Dist: cfig[cli] (>=0.2.3,<=0.4.0)
Requires-Dist: python-telegram-bot (>=20.0a1,<=21.0)
Project-URL: Documentation, https://forge.steffo.eu/steffo/threadkiller/wiki
Project-URL: Issues, https://forge.steffo.eu/steffo/threadkiller/issues
Project-URL: Source, https://forge.steffo.eu/steffo/threadkiller
Project-URL: Telegram, https://t.me/the_threadkiller_bot?startgroup=yes
